hello_package_test/__init__.py
hello_package_test-1.0.2.dist-info/METADATA
hello_package_test-1.0.2.dist-info/WHEEL
hello_package_test-1.0.2.dist-info/top_level.txt
hello_package_test-1.0.2.dist-info/RECORD
